mseep_spotify_mcp-0.2.6.dist-info/licenses/LICENSE
spotify_mcp/__init__.py
spotify_mcp/server.py
spotify_mcp/spotify_api.py
spotify_mcp/utils.py
mseep_spotify_mcp-0.2.6.dist-info/METADATA
mseep_spotify_mcp-0.2.6.dist-info/WHEEL
mseep_spotify_mcp-0.2.6.dist-info/entry_points.txt
mseep_spotify_mcp-0.2.6.dist-info/top_level.txt
mseep_spotify_mcp-0.2.6.dist-info/RECORD
